{
    "id": "ch.zhaw.ikitomo.defaultNeko",
    "name": "Default Neko",
    "settings": {
        "sleepChance": 0.5,
        "wakeChance": 0.5
    },
    "states": [
        {
            "type": "IDLE",
            "animationPrefix": "idle_",
            "animations": [
                {
                    "direction": "NONE",
                    "animationSuffix": "blink"
                },
                {
                    "direction": "NONE",
                    "animationSuffix": "think"
                },
                {
                    "direction": "NONE",
                    "animationSuffix": "groom"
                }
            ]
        },
        {
            "type": "YAWN",
            "animationPrefix": "yawn",
            "animations": [
                {
                    "direction": "NONE",
                    "animationSuffix": ""
                }
            ]
        },
        {
            "type": "SLEEP",
            "animationPrefix": "sleep",
            "animations": [
                {
                    "direction": "NONE",
                    "animationSuffix": ""
                }
            ]
        },
        {
            "type": "WAKE",
            "animationPrefix": "wake",
            "animations": [
                {
                    "direction": "NONE",
                    "animationSuffix": ""
                }
            ]
        },
        {
            "type": "RUN",
            "animationPrefix": "run_",
            "animations": [
                {
                    "direction": "UP",
                    "animationSuffix": "up"
                },
                {
                    "direction": "UP_RIGHT",
                    "animationSuffix": "up_right"
                },
                {
                    "direction": "RIGHT",
                    "animationSuffix": "right"
                },
                {
                    "direction": "DOWN_RIGHT",
                    "animationSuffix": "down_right"
                },
                {
                    "direction": "DOWN",
                    "animationSuffix": "down_right"
                },
                {
                    "direction": "DOWN_LEFT",
                    "animationSuffix": "down_left"
                },
                {
                    "direction": "LEFT",
                    "animationSuffix": "left"
                },
                {
                    "direction": "UP_LEFT",
                    "animationSuffix": "up_left"
                }
            ]
        }
    ]
}